README.rst
setup.py
rutherford/__init__.py
rutherford.egg-info/PKG-INFO
rutherford.egg-info/SOURCES.txt
rutherford.egg-info/dependency_links.txt
rutherford.egg-info/entry_points.txt
rutherford.egg-info/not-zip-safe
rutherford.egg-info/requires.txt
rutherford.egg-info/top_level.txt
rutherford/templates/feed.xml