Metadata-Version: 1.0
Name: rutherford
Version: 0.7.1
Summary: Atom feed for Tinkerer
Home-page: http://github.com/sgillies/rutherford
Author: Sean Gillies
Author-email: sean.gillies@gmail.com
License: BSD
Keywords: atom feed tinkerer
Platform: UNKNOWN
